bioio_nd2/__init__.py
bioio_nd2/plates.py
bioio_nd2/py.typed
bioio_nd2/reader.py
bioio_nd2/reader_metadata.py
bioio_nd2-1.6.2.dist-info/licenses/LICENSE
scripts/benchmark.py
bioio_nd2-1.6.2.dist-info/METADATA
bioio_nd2-1.6.2.dist-info/WHEEL
bioio_nd2-1.6.2.dist-info/entry_points.txt
bioio_nd2-1.6.2.dist-info/top_level.txt
bioio_nd2-1.6.2.dist-info/RECORD
