Metadata-Version: 2.4
Name: bioio-nd2
Version: 1.6.2
Summary: A BioIO reader plugin for reading ND2 images.
Author-email: bioio-devs <brian.whitney@alleninstitute.org>
License: MIT License
Project-URL: Homepage, https://github.com/bioio-devs/bioio-nd2
Project-URL: Bug Tracker, https://github.com/bioio-devs/bioio-nd2/issues
Project-URL: Documentation, https://bioio-devs.github.io/bioio-nd2
Project-URL: User Support, https://github.com/bioio-devs/bioio-nd2/issues
Classifier: Development Status :: 4 - Beta
Classifier: Natural Language :: English
Classifier: Programming Language :: Python :: 3.10
Classifier: Programming Language :: Python :: 3.11
Classifier: Programming Language :: Python :: 3.12
Classifier: Programming Language :: Python :: 3.13
Requires-Python: >=3.10
License-File: LICENSE
Requires-Dist: bioio-base>=3.0.0
Requires-Dist: nd2[legacy]>=0.10.3
Requires-Dist: dask[array]>=2021.4.1
Requires-Dist: fsspec>=2022.8.0
Requires-Dist: numpy>=1.16
Requires-Dist: PyYAML>=6.0
Requires-Dist: xarray>=0.16.1
Provides-Extra: lint
Requires-Dist: pre-commit>=2.20.0; extra == "lint"
Provides-Extra: test
Requires-Dist: coverage>=5.1; extra == "test"
Requires-Dist: pytest>=5.4.3; extra == "test"
Requires-Dist: pytest-cov>=2.9.0; extra == "test"
Requires-Dist: pytest-raises>=0.11; extra == "test"
Requires-Dist: types-PyYAML>=6.0.12.9; extra == "test"
Dynamic: license-file
